nblink/__init__.py
nblink/_version.py
nblink-0.1.12.data/data/share/jupyter/labextensions/nblink/package.json
nblink-0.1.12.data/data/share/jupyter/labextensions/nblink/static/345.97bfcac536baabbcbf8b.js
nblink-0.1.12.data/data/share/jupyter/labextensions/nblink/static/728.7cad898c8ef4e6c5d242.js
nblink-0.1.12.data/data/share/jupyter/labextensions/nblink/static/992.022f678437cf17acc0bb.js
nblink-0.1.12.data/data/share/jupyter/labextensions/nblink/static/remoteEntry.9368e771abf0629afc29.js
nblink-0.1.12.data/data/share/jupyter/labextensions/nblink/static/style.js
nblink-0.1.12.data/data/share/jupyter/labextensions/nblink/static/third-party-licenses.json
nblink-0.1.12.data/data/share/jupyter/labextensions/nblink/install.json
nblink-0.1.12.dist-info/METADATA
nblink-0.1.12.dist-info/WHEEL
nblink-0.1.12.dist-info/licenses/LICENSE
nblink-0.1.12.dist-info/RECORD
